wailer/__init__.py
wailer/apps.py
wailer/backends/__init__.py
wailer/backends/_utils.py
wailer/backends/mailjet.py
wailer/backends/mandrill.py
wailer/errors.py
wailer/interfaces.py
wailer/migrations/0001_initial.py
wailer/migrations/0002_alter_sms_sender.py
wailer/migrations/__init__.py
wailer/models.py
wailer/templates/wailer/style.html
wailer/templatetags/wailer.py
wailer/urls.py
wailer/utils.py
wailer/views.py
django_wailer-1.0.0b4.dist-info/LICENSE
django_wailer-1.0.0b4.dist-info/WHEEL
django_wailer-1.0.0b4.dist-info/METADATA
django_wailer-1.0.0b4.dist-info/RECORD
